dagster_mssql_bcp/__init__.py
dagster_mssql_bcp/bcp_core/__init__.py
dagster_mssql_bcp/bcp_core/asset_schema.py
dagster_mssql_bcp/bcp_core/bcp_core.py
dagster_mssql_bcp/bcp_core/bcp_io_manager_core.py
dagster_mssql_bcp/bcp_core/bcp_logger.py
dagster_mssql_bcp/bcp_core/bcp_resource.py
dagster_mssql_bcp/bcp_core/mssql_connection.py
dagster_mssql_bcp/bcp_core/shell.py
dagster_mssql_bcp/bcp_core/utils.py
dagster_mssql_bcp/bcp_pandas/__init__.py
dagster_mssql_bcp/bcp_pandas/pandas_mssql_bcp.py
dagster_mssql_bcp/bcp_pandas/pandas_mssql_io_manager.py
dagster_mssql_bcp/bcp_pandas/pandas_mssql_resource.py
dagster_mssql_bcp/bcp_polars/__init__.py
dagster_mssql_bcp/bcp_polars/polars_mssql_bcp.py
dagster_mssql_bcp/bcp_polars/polars_mssql_io_manager.py
dagster_mssql_bcp/bcp_polars/polars_mssql_resource.py
dagster_mssql_bcp-0.1.2.dist-info/METADATA
dagster_mssql_bcp-0.1.2.dist-info/WHEEL
dagster_mssql_bcp-0.1.2.dist-info/licenses/LICENSE.txt
dagster_mssql_bcp-0.1.2.dist-info/RECORD
