Metadata-Version: 2.4
Name: dagster-mssql-bcp
Version: 0.1.2
Project-URL: Homepage, https://github.com/cody-scott/dagster-mssql-bcp
Project-URL: Documentation, https://github.com/cody-scott/dagster-mssql-bcp/tree/main/docs
Project-URL: Repository, https://github.com/cody-scott/dagster-mssql-bcp.git
Project-URL: Issues, https://github.com/cody-scott/dagster-mssql-bcp/issues
Author-email: Cody Scott <carry-retort01@icloud.com>
License: MIT License
License-File: LICENSE.txt
Requires-Python: >=3.8
Requires-Dist: connectorx
Requires-Dist: dagster
Requires-Dist: pandas
Requires-Dist: pendulum
Requires-Dist: polars
Requires-Dist: pyarrow
Requires-Dist: pyodbc
Provides-Extra: dev
Requires-Dist: black; extra == 'dev'
Requires-Dist: dagster-webserver; extra == 'dev'
Requires-Dist: pytest; extra == 'dev'
Requires-Dist: pytest-cov; extra == 'dev'
Requires-Dist: pytest-mock; extra == 'dev'
Requires-Dist: ruff; extra == 'dev'
